{
  "project_info": {
    "project_number": "1045045917040",
    "project_id": "doctorg-abf97",
    "storage_bucket": "doctorg-abf97.appspot.com"
  },
  "client": [
    {
      "client_info": {
        "mobilesdk_app_id": "1:1045045917040:android:bea0822f594dbfc0320bb5",
        "android_client_info": {
          "package_name": "com.mamit.doctor"
        }
      },
      "oauth_client": [
        {
          "client_id": "1045045917040-pmv4ps2ovs8aho5ps67936im4sucps39.apps.googleusercontent.com",
          "client_type": 3
        }
      ],
      "api_key": [
        {
          "current_key": "AIzaSyAFSuIph2gwEiUyMQ1eQE_Qtl2xSJaK7ow"
        }
      ],
      "services": {
        "appinvite_service": {
          "other_platform_oauth_client": [
            {
              "client_id": "1045045917040-pmv4ps2ovs8aho5ps67936im4sucps39.apps.googleusercontent.com",
              "client_type": 3
            }
          ]
        }
      }
    }
  ],
  "configuration_version": "1"
}